supercharged/__init__.py
supercharged/lib/__init__.py
supercharged/lib/__main__.py
supercharged/lib/core.py
supercharged/lib/tests/__init__.py
supercharged/lib/tests/test_init.py
supercharged/templates/TRAFIK_TEMPLATE.yml
supercharged/templates/index.html
supercharged_cli-0.0.11.dist-info/LICENSE
supercharged_cli-0.0.11.dist-info/METADATA
supercharged_cli-0.0.11.dist-info/WHEEL
supercharged_cli-0.0.11.dist-info/entry_points.txt
supercharged_cli-0.0.11.dist-info/top_level.txt
supercharged_cli-0.0.11.dist-info/RECORD
